MANIFEST.in
README.md
setup.py
version.cache
beamism/__init__.py
beamism/pubsub_pipeline.py
beamism/utils.py
beamism.egg-info/PKG-INFO
beamism.egg-info/SOURCES.txt
beamism.egg-info/dependency_links.txt
beamism.egg-info/not-zip-safe
beamism.egg-info/requires.txt
beamism.egg-info/top_level.txt