Metadata-Version: 1.1
Name: beamism
Version: 0.3.6
Summary: welcome to beamism
Home-page: UNKNOWN
Author: UNKNOWN
Author-email: UNKNOWN
License: MIT
Platform: Linux
Platform: Darwin
Classifier: Programming Language :: Python :: 3
Classifier: License :: OSI Approved :: MIT License
